{
  "name": "MapAsset",
  "base": "PersistedModel",
  "idInjection": true,
  "options": {
    "validateUpsert": true
  },
  "properties": {
    "name": {
      "type": "string",
      "required": true
    },
    "description": {
      "type": "string"
    },
    "addressLine1": {
      "type": "string"
    },
    "addressLine2": {
      "type": "string"
    },
    "city": {
      "type": "string"
    },
    "state": {
      "type": "string"
    },
    "postalCode": {
      "type": "string"
    },
    "country": {
      "type": "string"
    },
    "geoJson": {
      "type": "string",
      "required": true
    }
  },
  "validations": [],
  "relations": {},
  "acls": [],
  "methods": {},
  "remoting" : {
    "normalizeHttpPath": true
  }
}
